pushmate/__init__.py
pushmate/clients/__init__.py
pushmate/clients/git.py
pushmate/clients/github.py
pushmate/clients/llm_client.py
pushmate/commands/__init__.py
pushmate/commands/commit.py
pushmate/commands/config.py
pushmate/commands/pr.py
pushmate/main.py
pushmate/utils/__init__.py
pushmate/utils/editor.py
pushmate/utils/messages.py
pushmate/utils/utils.py
pushmate-0.1.2.dist-info/LICENSE
pushmate-0.1.2.dist-info/METADATA
pushmate-0.1.2.dist-info/WHEEL
pushmate-0.1.2.dist-info/entry_points.txt
pushmate-0.1.2.dist-info/RECORD
